SystemtapXinshouZhinan/README.md
SystemtapXinshouZhinan/__init__.py
SystemtapXinshouZhinan/__main__.py
SystemtapXinshouZhinan/file.epub
SystemtapXinshouZhinan/index.html
SystemtapXinshouZhinan/css/__init__.py
SystemtapXinshouZhinan/css/annotations.css
SystemtapXinshouZhinan/css/main.css
SystemtapXinshouZhinan/css/normalize.css
SystemtapXinshouZhinan/css/popup.css
SystemtapXinshouZhinan/font/__init__.py
SystemtapXinshouZhinan/font/fontello.eot
SystemtapXinshouZhinan/font/fontello.svg
SystemtapXinshouZhinan/font/fontello.ttf
SystemtapXinshouZhinan/font/fontello.woff
SystemtapXinshouZhinan/img/__init__.py
SystemtapXinshouZhinan/img/annotator-glyph-sprite.png
SystemtapXinshouZhinan/img/annotator-icon-sprite.png
SystemtapXinshouZhinan/img/apple-touch-icon.png
SystemtapXinshouZhinan/img/cancelfullscreen.png
SystemtapXinshouZhinan/img/close.png
SystemtapXinshouZhinan/img/fullscreen.png
SystemtapXinshouZhinan/img/loader.gif
SystemtapXinshouZhinan/img/menu-icon.png
SystemtapXinshouZhinan/img/save.png
SystemtapXinshouZhinan/img/saved.png
SystemtapXinshouZhinan/img/settings-s.png
SystemtapXinshouZhinan/img/settings.png
SystemtapXinshouZhinan/img/star.png
SystemtapXinshouZhinan/js/__init__.py
SystemtapXinshouZhinan/js/epub.js
SystemtapXinshouZhinan/js/epub.min.js
SystemtapXinshouZhinan/js/epub.min.map
SystemtapXinshouZhinan/js/hooks.min.js
SystemtapXinshouZhinan/js/hooks.min.map
SystemtapXinshouZhinan/js/reader.js
SystemtapXinshouZhinan/js/reader.js.map
SystemtapXinshouZhinan/js/reader.min.js
SystemtapXinshouZhinan/js/reader.min.map
SystemtapXinshouZhinan/js/hooks/__init__.py
SystemtapXinshouZhinan/js/hooks/extensions/__init__.py
SystemtapXinshouZhinan/js/hooks/extensions/highlight.js
SystemtapXinshouZhinan/js/libs/__init__.py
SystemtapXinshouZhinan/js/libs/jquery.min.js
SystemtapXinshouZhinan/js/libs/localforage.min.js
SystemtapXinshouZhinan/js/libs/screenfull.js
SystemtapXinshouZhinan/js/libs/screenfull.min.js
SystemtapXinshouZhinan/js/libs/zip.min.js
systemtap_xinshou_zhinan-2024.3.2.0.dist-info/METADATA
systemtap_xinshou_zhinan-2024.3.2.0.dist-info/WHEEL
systemtap_xinshou_zhinan-2024.3.2.0.dist-info/entry_points.txt
systemtap_xinshou_zhinan-2024.3.2.0.dist-info/top_level.txt
systemtap_xinshou_zhinan-2024.3.2.0.dist-info/RECORD
